{
  "title": "todo mvc",
  "scene": "collection",
  "scalar_counter": null,
  "timer_counter": null,
  "collection": {
    "initial_titles": [
      "Buy groceries",
      "Clean room"
    ],
    "append_from_text_input": true,
    "toggle_all_from_checkbox": true,
    "clear_completed_from_button": true,
    "filters": [
      "all",
      "active",
      "completed"
    ],
    "item_checkbox_toggle": true,
    "item_remove_button": true
  },
  "table": null,
  "playfield": null,
  "physical_debug": false
}